odoo/addons/project_milestone/README.rst
odoo/addons/project_milestone/__init__.py
odoo/addons/project_milestone/__manifest__.py
odoo/addons/project_milestone/i18n/it.po
odoo/addons/project_milestone/i18n/project_milestone.pot
odoo/addons/project_milestone/migrations/15.0.1.0.0/pre-migration.py
odoo/addons/project_milestone/readme/CONTRIBUTORS.rst
odoo/addons/project_milestone/readme/DESCRIPTION.rst
odoo/addons/project_milestone/static/description/icon.png
odoo/addons/project_milestone/static/description/index.html
odoo_addon_project_milestone-15.0.1.0.1.3.dist-info/METADATA
odoo_addon_project_milestone-15.0.1.0.1.3.dist-info/WHEEL
odoo_addon_project_milestone-15.0.1.0.1.3.dist-info/top_level.txt
odoo_addon_project_milestone-15.0.1.0.1.3.dist-info/RECORD
